jupyterlab_markup/__init__.py
jupyterlab_markup/_version.py
jupyterlab_markup/labextension/package.json
jupyterlab_markup/labextension/schemas/@agoose77/jupyterlab-markup/core.json
jupyterlab_markup/labextension/schemas/@agoose77/jupyterlab-markup/package.json.orig
jupyterlab_markup/labextension/static/178.db8e0b9e1152a67c0289.js
jupyterlab_markup/labextension/static/233.100b849061fc2de9beae.js
jupyterlab_markup/labextension/static/233.100b849061fc2de9beae.js.LICENSE.txt
jupyterlab_markup/labextension/static/293.205f6ae438ccb9d15783.js
jupyterlab_markup/labextension/static/295.e13d0a37105bea6f8030.js
jupyterlab_markup/labextension/static/372.be67bcdb582d7410db71.js
jupyterlab_markup/labextension/static/384.219fa476cf5271ea0522.js
jupyterlab_markup/labextension/static/645.4c06d014279605e38ff8.js
jupyterlab_markup/labextension/static/651.209aed53be810bb8ed58.js
jupyterlab_markup/labextension/static/665.1e73a891ac7d7f84698f.js
jupyterlab_markup/labextension/static/980.884690f5fb2517d75217.js
jupyterlab_markup/labextension/static/980.fb2a5dd327092a504396.js
jupyterlab_markup/labextension/static/986.3edd54916b6b428adfdf.js
jupyterlab_markup/labextension/static/986.3edd54916b6b428adfdf.js.LICENSE.txt
jupyterlab_markup/labextension/static/999.7180abbfe6397cf5c8af.js
jupyterlab_markup/labextension/static/999.cd895bd57407720ae82f.js
jupyterlab_markup/labextension/static/c7a00d80d6ff5608e4df.module.wasm
jupyterlab_markup/labextension/static/remoteEntry.8e7eaccf88569d554db8.js
jupyterlab_markup/labextension/static/remoteEntry.b885f44022afff6e172a.js
jupyterlab_markup/labextension/static/remoteEntry.d255d0539eb6d4785fa2.js
jupyterlab_markup/labextension/static/style.js
jupyterlab_markup/labextension/static/third-party-licenses.json
jupyterlab_markup-2.0.0.data/data/share/jupyter/labextensions/@agoose77/jupyterlab-markup/install.json
jupyterlab_markup-2.0.0.data/data/share/jupyter/labextensions/@agoose77/jupyterlab-markup/package.json
jupyterlab_markup-2.0.0.dist-info/LICENSE
jupyterlab_markup-2.0.0.dist-info/METADATA
jupyterlab_markup-2.0.0.dist-info/WHEEL
jupyterlab_markup-2.0.0.dist-info/top_level.txt
jupyterlab_markup-2.0.0.dist-info/RECORD
