Metadata-Version: 2.1
Name: jupyterlab-markup
Version: 2.0.0
Summary: Extensible markdown rendering support in markdown
Home-page: https://github.com/agoose77/jupyterlab-markup.git
Author: Angus Hollands
Author-email: goosey15@gmail.com
License: BSD-3-Clause
Project-URL: Bug Tracker, https://github.com/agoose77/jupyterlab-markup/issues
Keywords: Jupyter,JupyterLab,JupyterLab3,Markdown,MarkdownIt
Platform: Linux
Platform: Mac OS X
Platform: Windows
Classifier: License :: OSI Approved :: BSD License
Classifier: Programming Language :: Python
Classifier: Programming Language :: Python :: 3
Classifier: Programming Language :: Python :: 3.6
Classifier: Programming Language :: Python :: 3.7
Classifier: Programming Language :: Python :: 3.8
Classifier: Framework :: Jupyter
Classifier: Framework :: Jupyter :: JupyterLab
Classifier: Framework :: Jupyter :: JupyterLab :: 3
Classifier: Framework :: Jupyter :: JupyterLab :: Extensions
Classifier: Framework :: Jupyter :: JupyterLab :: Extensions :: Mime Renderers
Classifier: Framework :: Jupyter :: JupyterLab :: Extensions :: Prebuilt
Requires-Python: >=3.7
License-File: LICENSE
Requires-Dist: jupyterlab (==3.*,>=3.0)
